{
    "workers": [
        {
            "name": "황지훈",
            "ss": true,
            "exempted_reason": "na",
            "exempted_start_date": "na",
            "exempted_end_date": "na"
        },
        {
            "name": "변희원",
            "ss": true,
            "exempted_reason": "na",
            "exempted_start_date": "na",
            "exempted_end_date": "na"
        },
        {
            "name": "한철웅", 
            "ss": true,
            "exempted_reason": "na",
            "exempted_start_date": "na",
            "exempted_end_date": "na"
        },
        {
            "name": "김동수",
            "ss": true,
            "exempted_reason": "na",
            "exempted_start_date": "na",
            "exempted_end_date": "na"
        },
        {
            "name": "최선웅",
            "ss": false,
            "exempted_reason": "na",
            "exempted_start_date": "na",
            "exempted_end_date": "na"
        },
        {
            "name": "김태언",
            "ss": false,
            "exempted_reason": "na",
            "exempted_start_date": "na",
            "exempted_end_date": "na"
        },
        {
            "name": "민준식",
            "ss": false,
            "exempted_reason":"na",
            "exempted_start_date": "na",
            "exempted_end_date": "na"
        },
        {
            "name": "최진영",
            "ss": false,
            "exempted_reason": "na",
            "exempted_start_date": "na",
            "exempted_end_date": "na"
        },
        {
            "name": "장형택",
            "ss": false,
            "exempted_reason": "na",
            "exempted_start_date": "na",
            "exempted_end_date": "na"
        },
        {
            "name": "김병호",
            "ss": false,
            "exempted_reason": "na",
            "exempted_start_date": "na",
            "exempted_end_date": "na"
        },
        {
            "name": "이융",
            "ss": false,
            "exempted_reason": "na",
            "exempted_start_date": "na",
            "exempted_end_date": "na"
        }
    ]
}